senzwifi/__init__.py
senzwifi/__main__.py
senzwifi/session.py
senzwifi/urls.py
senzwifi-0.0.1.dist-info/LICENSE
senzwifi-0.0.1.dist-info/METADATA
senzwifi-0.0.1.dist-info/WHEEL
senzwifi-0.0.1.dist-info/entry_points.txt
senzwifi-0.0.1.dist-info/top_level.txt
senzwifi-0.0.1.dist-info/RECORD
