Metadata-Version: 2.1
Name: senzwifi
Version: 0.0.1
Summary: Python module for working with the senz wifi climate devices 
Home-page: https://github.com/sockless-coding/python-senz-wifi-module
Author: sockless-coding
License: MIT
Keywords: home automation senz climate
Platform: UNKNOWN
Classifier: Topic :: Home Automation
Classifier: License :: OSI Approved :: MIT License
Classifier: Programming Language :: Python :: 3.4
Classifier: Programming Language :: Python :: 3.5
Requires-Dist: requests (>=2.20.0)
